INSTALL.rst
LICENSE
MANIFEST.in
README.rst
VERSION
requirements.txt
setup.cfg
setup.py
tasks.py
src/pytugacore/__init__.py
src/pytugacore/__main__.py
src/pytugacore/__meta__.py
src/pytugacore/console.py
src/pytugacore/core.py
src/pytugacore/jupyter.py
src/pytugacore/keyword.py
src/pytugacore/lexer.py
src/pytugacore/transpyler.py
src/pytugacore.egg-info/PKG-INFO
src/pytugacore.egg-info/SOURCES.txt
src/pytugacore.egg-info/dependency_links.txt
src/pytugacore.egg-info/not-zip-safe
src/pytugacore.egg-info/requires.txt
src/pytugacore.egg-info/top_level.txt
src/pytugacore/lib/__init__.py
src/pytugacore/lib/curses.py
src/pytugacore/lib/tuga_draw.py
src/pytugacore/lib/tuga_io.py
src/pytugacore/lib/tuga_math.py
src/pytugacore/lib/tuga_std.py
src/pytugacore/lib/tuga_strings.py
src/pytugacore/tests/__init__.py
src/pytugacore/tests/__main__.py
src/pytugacore/tests/test_core.py
src/pytugacore/tests/test_documentation.py
src/pytugacore/tests/test_errors.py
src/pytugacore/tests/test_language.py
src/pytugacore/tests/test_pytugacore.py
src/pytugacore/tests/test_runtime.py